{"variables":[],"info":{"name":"","_postman_id":"c6cb47d4-d73b-47df-b564-0d1b8645a41b","description":"","schema":"https:\/\/schema.getpostman.com\/json\/collection\/v2.0.0\/collection.json"},"item":[{"name":"general","description":"","item":[{"name":"Display Swagger API page.","request":{"url":"http:\/\/localhost\/api\/documentation","method":"GET","body":{"mode":"formdata","formdata":[]},"description":"","response":[]}},{"name":"Dump api-docs.json content endpoint.","request":{"url":"http:\/\/localhost\/docs\/{jsonFile?}","method":"GET","body":{"mode":"formdata","formdata":[]},"description":"","response":[]}},{"name":"http:\/\/localhost\/docs\/asset\/{asset}","request":{"url":"http:\/\/localhost\/docs\/asset\/{asset}","method":"GET","body":{"mode":"formdata","formdata":[]},"description":"","response":[]}},{"name":"Display Oauth2 callback pages.","request":{"url":"http:\/\/localhost\/api\/oauth2-callback","method":"GET","body":{"mode":"formdata","formdata":[]},"description":"","response":[]}},{"name":"Display a listing of the resource.","request":{"url":"http:\/\/localhost\/api\/user","method":"GET","body":{"mode":"formdata","formdata":[]},"description":"","response":[]}},{"name":"Show the form for creating a new resource.","request":{"url":"http:\/\/localhost\/api\/user\/create","method":"GET","body":{"mode":"formdata","formdata":[]},"description":"","response":[]}},{"name":"Store a newly created resource in storage.","request":{"url":"http:\/\/localhost\/api\/user","method":"POST","body":{"mode":"formdata","formdata":[]},"description":"","response":[]}},{"name":"Display the specified resource.","request":{"url":"http:\/\/localhost\/api\/user\/{user}","method":"GET","body":{"mode":"formdata","formdata":[]},"description":"","response":[]}},{"name":"Show the form for editing the specified resource.","request":{"url":"http:\/\/localhost\/api\/user\/{user}\/edit","method":"GET","body":{"mode":"formdata","formdata":[]},"description":"","response":[]}},{"name":"Update the specified resource in storage.","request":{"url":"http:\/\/localhost\/api\/user\/{user}","method":"PUT","body":{"mode":"formdata","formdata":[]},"description":"","response":[]}},{"name":"Remove the specified resource from storage.","request":{"url":"http:\/\/localhost\/api\/user\/{user}","method":"DELETE","body":{"mode":"formdata","formdata":[]},"description":"","response":[]}},{"name":"Display a listing of the resource.","request":{"url":"http:\/\/localhost\/api\/article","method":"GET","body":{"mode":"formdata","formdata":[]},"description":"","response":[]}},{"name":"Show the form for creating a new resource.","request":{"url":"http:\/\/localhost\/api\/article\/create","method":"GET","body":{"mode":"formdata","formdata":[]},"description":"","response":[]}},{"name":"Store a newly created resource in storage.","request":{"url":"http:\/\/localhost\/api\/article","method":"POST","body":{"mode":"formdata","formdata":[]},"description":"","response":[]}},{"name":"Display the specified resource.","request":{"url":"http:\/\/localhost\/api\/article\/{article}","method":"GET","body":{"mode":"formdata","formdata":[]},"description":"","response":[]}},{"name":"Show the form for editing the specified resource.","request":{"url":"http:\/\/localhost\/api\/article\/{article}\/edit","method":"GET","body":{"mode":"formdata","formdata":[]},"description":"","response":[]}},{"name":"Update the specified resource in storage.","request":{"url":"http:\/\/localhost\/api\/article\/{article}","method":"PUT","body":{"mode":"formdata","formdata":[]},"description":"","response":[]}},{"name":"Remove the specified resource from storage.","request":{"url":"http:\/\/localhost\/api\/article\/{article}","method":"DELETE","body":{"mode":"formdata","formdata":[]},"description":"","response":[]}},{"name":"Display a listing of the resource.","request":{"url":"http:\/\/localhost\/api\/comment","method":"GET","body":{"mode":"formdata","formdata":[]},"description":"","response":[]}},{"name":"Show the form for creating a new resource.","request":{"url":"http:\/\/localhost\/api\/comment\/create","method":"GET","body":{"mode":"formdata","formdata":[]},"description":"","response":[]}},{"name":"Store a newly created resource in storage.","request":{"url":"http:\/\/localhost\/api\/comment","method":"POST","body":{"mode":"formdata","formdata":[]},"description":"","response":[]}},{"name":"Display the specified resource.","request":{"url":"http:\/\/localhost\/api\/comment\/{comment}","method":"GET","body":{"mode":"formdata","formdata":[]},"description":"","response":[]}},{"name":"Show the form for editing the specified resource.","request":{"url":"http:\/\/localhost\/api\/comment\/{comment}\/edit","method":"GET","body":{"mode":"formdata","formdata":[]},"description":"","response":[]}},{"name":"Update the specified resource in storage.","request":{"url":"http:\/\/localhost\/api\/comment\/{comment}","method":"PUT","body":{"mode":"formdata","formdata":[]},"description":"","response":[]}},{"name":"Remove the specified resource from storage.","request":{"url":"http:\/\/localhost\/api\/comment\/{comment}","method":"DELETE","body":{"mode":"formdata","formdata":[]},"description":"","response":[]}}]}]}